nanoml/__init__.py
nanoml/data.py
nanoml/device.py
nanoml/dtype.py
nanoml-0.1.4.dist-info/METADATA
nanoml-0.1.4.dist-info/WHEEL
nanoml-0.1.4.dist-info/licenses/LICENSE
nanoml-0.1.4.dist-info/RECORD
