Metadata-Version: 2.4
Name: nanoml
Version: 0.1.4
Summary: Small utility functions for machine learning
Project-URL: Homepage, https://github.com/dipta007/nanoml
Project-URL: Bug Tracker, https://github.com/dipta007/nanoml/issues
Author-email: Shubhashis Roy Dipta <iamdipta@gmail.com>
License-Expression: MIT
License-File: LICENSE
Keywords: AI,CV,Computer Vision,Deep Learning,Machine Learning,NLP,NanoML,Natural Language Processing,Utility Functions,machine learning,utility functions
Classifier: Development Status :: 3 - Alpha
Classifier: Intended Audience :: Science/Research
Classifier: License :: OSI Approved :: MIT License
Classifier: Operating System :: OS Independent
Classifier: Programming Language :: Python :: 3.8
Classifier: Programming Language :: Python :: 3.9
Classifier: Programming Language :: Python :: 3.10
Classifier: Programming Language :: Python :: 3.11
Classifier: Programming Language :: Python :: 3.12
Requires-Python: >=3.8
Requires-Dist: datasets>=3.1.0
Requires-Dist: numpy>=1.24.4
Requires-Dist: torch>=2.5.0
